metrit/Monitoring.py
metrit/StatCollector.py
metrit/Stats.py
metrit/__init__.py
metrit/core.py
metrit/utils.py
metrit-0.1.6.dist-info/LICENSE
metrit-0.1.6.dist-info/METADATA
metrit-0.1.6.dist-info/WHEEL
metrit-0.1.6.dist-info/top_level.txt
metrit-0.1.6.dist-info/RECORD
