Metadata-Version: 2.1
Name: metrit
Version: 0.1.6
Summary: A dead simple resources monitoring decorator
Author-email: Mario Crespo <info@mariocrespo.es>
License: MIT License
Project-URL: Repository, https://github.com/mcrespoae/metrit
Classifier: Development Status :: 4 - Beta
Classifier: Programming Language :: Python :: 3
Classifier: License :: OSI Approved :: MIT License
Classifier: Operating System :: OS Independent
Classifier: Intended Audience :: Developers
Requires-Python: >=3.8
License-File: LICENSE
Requires-Dist: psutil ==6.0.0
Requires-Dist: multiprocess ==0.70.17
